_xbart_cpp_.cpython-36m-darwin.so
xbart/__init__.py
xbart/xbart_cpp_.py
xbart/xbart_python.py
xbart-0.1.8.dist-info/METADATA
xbart-0.1.8.dist-info/WHEEL
xbart-0.1.8.dist-info/top_level.txt
xbart-0.1.8.dist-info/RECORD
