Metadata-Version: 2.1
Name: xbart
Version: 0.1.8
Summary: XBART project
Home-page: UNKNOWN
Author: Jingyu He, Saar Yalov, P. Richard Hahn
Author-email: saar.yalov@gmail.com
License: Apache-2.0
Platform: UNKNOWN
Requires-Python: >3.5
Requires-Dist: numpy
